potato_util/__init__.py
potato_util/__version__.py
potato_util/_base.py
potato_util/dt.py
potato_util/generator.py
potato_util/sanitizer.py
potato_util/secure.py
potato_util/validator.py
potato_util/constants/__init__.py
potato_util/constants/_base.py
potato_util/constants/_enum.py
potato_util/constants/_regex.py
potato_util/http/__init__.py
potato_util/http/_async.py
potato_util/http/_base.py
potato_util/http/_sync.py
potato_util/http/fastapi.py
potato_util/io/__init__.py
potato_util/io/_async.py
potato_util/io/_sync.py
potato_util-0.0.5.dist-info/licenses/LICENSE.txt
potato_util-0.0.5.dist-info/METADATA
potato_util-0.0.5.dist-info/WHEEL
potato_util-0.0.5.dist-info/top_level.txt
potato_util-0.0.5.dist-info/RECORD
