Metadata-Version: 2.4
Name: potato_util
Version: 0.0.5
Summary: 'potato_util' is collection of simple useful utils package for python.
Author-email: Batkhuu Byambajav <batkhuu10@gmail.com>
Project-URL: Homepage, https://github.com/bybatkhuu/module-python-utils
Project-URL: Documentation, https://pyutils-docs.bybatkhuu.dev
Project-URL: Repository, https://github.com/bybatkhuu/module-python-utils.git
Project-URL: Issues, https://github.com/bybatkhuu/module-python-utils/issues
Project-URL: Changelog, https://github.com/bybatkhuu/module-python-utils/blob/main/CHANGELOG.md
Keywords: potato_util,utils,utilities,tools,helpers
Classifier: Development Status :: 4 - Beta
Classifier: Intended Audience :: Developers
Classifier: Topic :: Software Development :: Libraries
Classifier: Operating System :: OS Independent
Classifier: Programming Language :: Python :: 3
Classifier: Programming Language :: Python :: 3.10
Classifier: Programming Language :: Python :: 3.11
Classifier: Programming Language :: Python :: 3.12
Classifier: Programming Language :: Python :: 3.13
Requires-Python: <4.0,>=3.10
License-File: LICENSE.txt
Requires-Dist: python-dotenv<2.0.0,>=1.0.1
Requires-Dist: pydantic[email,timezone]<3.0.0,>=2.0.3
Requires-Dist: pydantic-settings<3.0.0,>=2.2.1
Provides-Extra: async
Requires-Dist: aiofiles<25.0.0,>=24.1.0; extra == "async"
Requires-Dist: aioshutil<2.0.0,>=1.5; extra == "async"
Requires-Dist: aiohttp<4.0.0,>=3.11.18; extra == "async"
Provides-Extra: fastapi
Requires-Dist: fastapi<1.0.0,>=0.109.2; extra == "fastapi"
Provides-Extra: all
Requires-Dist: aiofiles<25.0.0,>=24.1.0; extra == "all"
Requires-Dist: aioshutil<2.0.0,>=1.5; extra == "all"
Requires-Dist: aiohttp<4.0.0,>=3.11.18; extra == "all"
Requires-Dist: fastapi<1.0.0,>=0.109.2; extra == "all"
Provides-Extra: test
Requires-Dist: aiofiles<25.0.0,>=24.1.0; extra == "test"
Requires-Dist: aioshutil<2.0.0,>=1.5; extra == "test"
Requires-Dist: aiohttp<4.0.0,>=3.11.18; extra == "test"
Requires-Dist: fastapi<1.0.0,>=0.109.2; extra == "test"
Requires-Dist: pytest<9.0.0,>=8.0.2; extra == "test"
Requires-Dist: pytest-cov<8.0.0,>=5.0.0; extra == "test"
Requires-Dist: pytest-xdist<4.0.0,>=3.6.1; extra == "test"
Requires-Dist: pytest-benchmark<6.0.0,>=5.0.1; extra == "test"
Provides-Extra: build
Requires-Dist: setuptools<81.0.0,>=70.3.0; extra == "build"
Requires-Dist: wheel<1.0.0,>=0.43.0; extra == "build"
Requires-Dist: build<2.0.0,>=1.1.1; extra == "build"
Requires-Dist: twine<7.0.0,>=6.0.1; extra == "build"
Provides-Extra: docs
Requires-Dist: pylint<4.0.0,>=3.0.4; extra == "docs"
Requires-Dist: mkdocs-material<10.0.0,>=9.5.50; extra == "docs"
Requires-Dist: mkdocs-awesome-nav<4.0.0,>=3.0.0; extra == "docs"
Requires-Dist: mkdocstrings[python]<1.0.0,>=0.24.3; extra == "docs"
Requires-Dist: mike<3.0.0,>=2.1.3; extra == "docs"
Provides-Extra: dev
Requires-Dist: aiofiles<25.0.0,>=24.1.0; extra == "dev"
Requires-Dist: aioshutil<2.0.0,>=1.5; extra == "dev"
Requires-Dist: aiohttp<4.0.0,>=3.11.18; extra == "dev"
Requires-Dist: fastapi<1.0.0,>=0.109.2; extra == "dev"
Requires-Dist: pytest<9.0.0,>=8.0.2; extra == "dev"
Requires-Dist: pytest-cov<8.0.0,>=5.0.0; extra == "dev"
Requires-Dist: pytest-xdist<4.0.0,>=3.6.1; extra == "dev"
Requires-Dist: pytest-benchmark<6.0.0,>=5.0.1; extra == "dev"
Requires-Dist: setuptools<81.0.0,>=70.3.0; extra == "dev"
Requires-Dist: wheel<1.0.0,>=0.43.0; extra == "dev"
Requires-Dist: build<2.0.0,>=1.1.1; extra == "dev"
Requires-Dist: twine<7.0.0,>=6.0.1; extra == "dev"
Requires-Dist: pylint<4.0.0,>=3.0.4; extra == "dev"
Requires-Dist: mkdocs-material<10.0.0,>=9.5.50; extra == "dev"
Requires-Dist: mkdocs-awesome-nav<4.0.0,>=3.0.0; extra == "dev"
Requires-Dist: mkdocstrings[python]<1.0.0,>=0.24.3; extra == "dev"
Requires-Dist: mike<3.0.0,>=2.1.3; extra == "dev"
Requires-Dist: pyright<2.0.0,>=1.1.392; extra == "dev"
Requires-Dist: pre-commit<5.0.0,>=4.0.1; extra == "dev"
Dynamic: license-file
